nf_prefix_tree.cpython-37m-darwin.so
prefix_tree.cpython-37m-darwin.so
nf_prefix_tree-0.1.0.dist-info/LICENSE
nf_prefix_tree-0.1.0.dist-info/METADATA
nf_prefix_tree-0.1.0.dist-info/WHEEL
nf_prefix_tree-0.1.0.dist-info/top_level.txt
nf_prefix_tree-0.1.0.dist-info/RECORD
