Metadata-Version: 2.1
Name: nf-prefix-tree
Version: 0.1.0
Summary: A datastructure for efficient storage of string data
Home-page: https://github.com/zmcgrath96/nf_prefix_tree
Author: Zachary McGrath
Author-email: zmcgrath96@gmail.com
License: UNKNOWN
Keywords: prefix bioinformatics substring string fast memory
Platform: UNKNOWN
